[
  {
    "hour": 0,
    "predicted_class": "MEDIUM",
    "predicted_kw": 5.8,
    "confidence": 76.5,
    "bhatan_kw": 2.03,
    "somathne_kw": 1.16,
    "palaspe_kw": 1.45,
    "kalamboli_kw": 1.16
  },
  {
    "hour": 1,
    "predicted_class": "MEDIUM",
    "predicted_kw": 5.8,
    "confidence": 68.0,
    "bhatan_kw": 2.03,
    "somathne_kw": 1.16,
    "palaspe_kw": 1.45,
    "kalamboli_kw": 1.16
  },
  {
    "hour": 2,
    "predicted_class": "MEDIUM",
    "predicted_kw": 5.8,
    "confidence": 67.2,
    "bhatan_kw": 2.03,
    "somathne_kw": 1.16,
    "palaspe_kw": 1.45,
    "kalamboli_kw": 1.16
  },
  {
    "hour": 3,
    "predicted_class": "MEDIUM",
    "predicted_kw": 5.8,
    "confidence": 78.5,
    "bhatan_kw": 2.03,
    "somathne_kw": 1.16,
    "palaspe_kw": 1.45,
    "kalamboli_kw": 1.16
  },
  {
    "hour": 4,
    "predicted_class": "MEDIUM",
    "predicted_kw": 5.8,
    "confidence": 57.6,
    "bhatan_kw": 2.03,
    "somathne_kw": 1.16,
    "palaspe_kw": 1.45,
    "kalamboli_kw": 1.16
  },
  {
    "hour": 5,
    "predicted_class": "MEDIUM",
    "predicted_kw": 5.8,
    "confidence": 74.6,
    "bhatan_kw": 2.03,
    "somathne_kw": 1.16,
    "palaspe_kw": 1.45,
    "kalamboli_kw": 1.16
  },
  {
    "hour": 6,
    "predicted_class": "MEDIUM",
    "predicted_kw": 5.8,
    "confidence": 55.2,
    "bhatan_kw": 2.03,
    "somathne_kw": 1.16,
    "palaspe_kw": 1.45,
    "kalamboli_kw": 1.16
  },
  {
    "hour": 7,
    "predicted_class": "MEDIUM",
    "predicted_kw": 5.8,
    "confidence": 48.9,
    "bhatan_kw": 2.03,
    "somathne_kw": 1.16,
    "palaspe_kw": 1.45,
    "kalamboli_kw": 1.16
  },
  {
    "hour": 8,
    "predicted_class": "MEDIUM",
    "predicted_kw": 5.8,
    "confidence": 84.0,
    "bhatan_kw": 2.03,
    "somathne_kw": 1.16,
    "palaspe_kw": 1.45,
    "kalamboli_kw": 1.16
  },
  {
    "hour": 9,
    "predicted_class": "HIGH",
    "predicted_kw": 8.4,
    "confidence": 52.7,
    "bhatan_kw": 2.94,
    "somathne_kw": 1.68,
    "palaspe_kw": 2.1,
    "kalamboli_kw": 1.68
  },
  {
    "hour": 10,
    "predicted_class": "MEDIUM",
    "predicted_kw": 5.8,
    "confidence": 83.1,
    "bhatan_kw": 2.03,
    "somathne_kw": 1.16,
    "palaspe_kw": 1.45,
    "kalamboli_kw": 1.16
  },
  {
    "hour": 11,
    "predicted_class": "HIGH",
    "predicted_kw": 8.4,
    "confidence": 57.1,
    "bhatan_kw": 2.94,
    "somathne_kw": 1.68,
    "palaspe_kw": 2.1,
    "kalamboli_kw": 1.68
  },
  {
    "hour": 12,
    "predicted_class": "MEDIUM",
    "predicted_kw": 5.8,
    "confidence": 92.0,
    "bhatan_kw": 2.03,
    "somathne_kw": 1.16,
    "palaspe_kw": 1.45,
    "kalamboli_kw": 1.16
  },
  {
    "hour": 13,
    "predicted_class": "MEDIUM",
    "predicted_kw": 5.8,
    "confidence": 95.6,
    "bhatan_kw": 2.03,
    "somathne_kw": 1.16,
    "palaspe_kw": 1.45,
    "kalamboli_kw": 1.16
  },
  {
    "hour": 14,
    "predicted_class": "MEDIUM",
    "predicted_kw": 5.8,
    "confidence": 51.1,
    "bhatan_kw": 2.03,
    "somathne_kw": 1.16,
    "palaspe_kw": 1.45,
    "kalamboli_kw": 1.16
  },
  {
    "hour": 15,
    "predicted_class": "MEDIUM",
    "predicted_kw": 5.8,
    "confidence": 62.7,
    "bhatan_kw": 2.03,
    "somathne_kw": 1.16,
    "palaspe_kw": 1.45,
    "kalamboli_kw": 1.16
  },
  {
    "hour": 16,
    "predicted_class": "HIGH",
    "predicted_kw": 8.4,
    "confidence": 59.4,
    "bhatan_kw": 2.94,
    "somathne_kw": 1.68,
    "palaspe_kw": 2.1,
    "kalamboli_kw": 1.68
  },
  {
    "hour": 17,
    "predicted_class": "HIGH",
    "predicted_kw": 8.4,
    "confidence": 50.1,
    "bhatan_kw": 2.94,
    "somathne_kw": 1.68,
    "palaspe_kw": 2.1,
    "kalamboli_kw": 1.68
  },
  {
    "hour": 18,
    "predicted_class": "MEDIUM",
    "predicted_kw": 5.8,
    "confidence": 86.4,
    "bhatan_kw": 2.03,
    "somathne_kw": 1.16,
    "palaspe_kw": 1.45,
    "kalamboli_kw": 1.16
  },
  {
    "hour": 19,
    "predicted_class": "MEDIUM",
    "predicted_kw": 5.8,
    "confidence": 95.3,
    "bhatan_kw": 2.03,
    "somathne_kw": 1.16,
    "palaspe_kw": 1.45,
    "kalamboli_kw": 1.16
  },
  {
    "hour": 20,
    "predicted_class": "MEDIUM",
    "predicted_kw": 5.8,
    "confidence": 57.7,
    "bhatan_kw": 2.03,
    "somathne_kw": 1.16,
    "palaspe_kw": 1.45,
    "kalamboli_kw": 1.16
  },
  {
    "hour": 21,
    "predicted_class": "MEDIUM",
    "predicted_kw": 5.8,
    "confidence": 61.3,
    "bhatan_kw": 2.03,
    "somathne_kw": 1.16,
    "palaspe_kw": 1.45,
    "kalamboli_kw": 1.16
  },
  {
    "hour": 22,
    "predicted_class": "MEDIUM",
    "predicted_kw": 5.8,
    "confidence": 89.0,
    "bhatan_kw": 2.03,
    "somathne_kw": 1.16,
    "palaspe_kw": 1.45,
    "kalamboli_kw": 1.16
  },
  {
    "hour": 23,
    "predicted_class": "MEDIUM",
    "predicted_kw": 5.8,
    "confidence": 98.1,
    "bhatan_kw": 2.03,
    "somathne_kw": 1.16,
    "palaspe_kw": 1.45,
    "kalamboli_kw": 1.16
  }
]